wook/__init__.py
wook/__main__.py
wook-0.1.1.dist-info/LICENSE
wook-0.1.1.dist-info/METADATA
wook-0.1.1.dist-info/WHEEL
wook-0.1.1.dist-info/entry_points.txt
wook-0.1.1.dist-info/top_level.txt
wook-0.1.1.dist-info/RECORD
