Metadata-Version: 2.1
Name: wook
Version: 0.1.1
Summary: Wook says hello!
Home-page: https://github.com/affjljoo3581/wook
Author: Jungwoo Park
Author-email: affjljoo3581@gmail.com
License: Apache-2.0
Keywords: wook,lee wook
Platform: UNKNOWN
Classifier: Environment :: Console
Classifier: Operating System :: OS Independent
Classifier: Programming Language :: Python :: 3
Classifier: Programming Language :: Python :: 3.6
Classifier: Programming Language :: Python :: 3.7
Classifier: Programming Language :: Python :: 3.8
Requires-Python: >=3
